{
    "alannah4170": {
        "teams": [
            {
                "id": 15306,
                "shortname": "in_memory_of_shirley",
                "name": "In Memory of Shirley",
                "category": "Memorials",
                "image": {
                    "id": 608549,
                    "template_id": 1
                },
                "whereabouts": "Vancouver",
                "loan_because": "We want to honour the memory of a kind, helpful, and generous woman who helped to make the world a better place. ",
                "description": "",
                "website_url": "",
                "team_since": "2010-09-27T23:20:29Z",
                "membership_type": "closed",
                "member_count": 5,
                "loan_count": 142,
                "loaned_amount": 3575
            }
        ]
    }
}{
    "alisha5308": {
        "teams": []
    }
}{
    "andrew52475083": {
        "teams": []
    }
}{
    "AD8484": {
        "teams": [
            {
                "id": 94,
                "shortname": "atheists",
                "name": "Atheists, Agnostics, Skeptics, Freethinkers, Secular Humanists and the Non-Religious",
                "category": "Common Interest",
                "image": {
                    "id": 1401504,
                    "template_id": 1
                },
                "whereabouts": "Earth",
                "loan_because": "We care about human beings and understand that it takes people to help people.",
                "description": "We are one human family, and we know that people can do good without believing in a god.\r\n\r\nThe Plus sign in the A+ Team logo reflects the fact that the team comprises Atheists, PLUS Agnostics, Skeptics, Freethinkers, Secular Humanists, and Non-Religious members.  A+ is also a symbol of excellence.\r\n\r\n***TEAM WEBSITE***\r\nhttp://apluskiva.wordpress.com/\r\n\r\n***TEAM RESOURCES***\r\nSecular Loans\r\nhttp://goo.gl/wtDkJ\r\n\r\nField Partners - Social and Secular Ratings:\r\nwww.tinyurl.com/AASFSHNR-MFIs\r\n\r\n***OTHER RESOURCES:***\r\nStarfish List:\r\nhttp://starfish.dynalias.org/\r\n\r\nKivaLens:\r\nhttp://www.kivalens.org/\r\n\r\nToolkit for analyzing Kiva data:\r\nhttp://build.kiva.org/",
                "website_url": "http://apluskiva.wordpress.com/",
                "team_since": "2008-08-29T03:40:31Z",
                "membership_type": "open",
                "member_count": 30456,
                "loan_count": 611640,
                "loaned_amount": 17850225
            },
            {
                "id": 6348,
                "shortname": "results",
                "name": "RESULTS (NC Triangle Chapter & Friends)",
                "category": "Clubs",
                "image": {
                    "id": 309660,
                    "template_id": 1
                },
                "whereabouts": "Around the world",
                "loan_because": "We believe in the power of microfinance!",
                "description": "RESULTS is a nonprofit grassroots advocacy organization committed to creating the political will to end hunger and the worst aspects of poverty. The NC Triangle Chapter (Raleigh, Durham, Chapel Hill) invites everyone from the RESULTS community and beyond to join :)\r\n\r\n**Disclaimer: This is an individual initiative by the NC Triangle Chapter, not an initiative by RESULTS.",
                "website_url": "www.results.org",
                "team_since": "2009-04-22T01:11:44Z",
                "membership_type": "open",
                "member_count": 20,
                "loan_count": 223,
                "loaned_amount": 5600
            },
            {
                "id": 394,
                "shortname": "nerdfighters",
                "name": "Nerdfighters",
                "category": "Common Interest",
                "image": {
                    "id": 1364412,
                    "template_id": 1
                },
                "whereabouts": "Nerdfighteria",
                "loan_because": "We aim to decrease world suck.\r\n\r\nAnd this is how:\r\nwww.eludehcs.no/kiva/nerdfighters/nerdfighters20120916.png by Nerdfighter Ole Bendik",
                "description": "We're Nerdfighters! We fight against suck; we fight for awesome! We fight using our brains, our hearts, our calculators, and our trombones.\r\n\r\nHappy lending!\r\n\r\nFollow us on twitter: https://twitter.com/KivaNerds",
                "website_url": "youtube.com/vlogbrothers",
                "team_since": "2008-09-02T16:26:24Z",
                "membership_type": "open",
                "member_count": 47565,
                "loan_count": 160855,
                "loaned_amount": 4745950
            }
        ]
    }
}{
    "shiro2784": {
        "teams": []
    }
}{
    "johannes8498": {
        "teams": []
    }
}{
    "victoria5992": {
        "teams": [
            {
                "id": 15147,
                "shortname": "we_are_here_for_you",
                "name": "We are here for You",
                "category": "Friends",
                "image": {
                    "id": 602494,
                    "template_id": 1
                },
                "whereabouts": "China",
                "loan_because": "We want to help people who want to help themsleves to have a better life.",
                "description": "We are  friends sharing the same opinion: we can do more to commit ourselves into the world",
                "website_url": "",
                "team_since": "2010-09-18T08:03:37Z",
                "membership_type": "open",
                "member_count": 20,
                "loan_count": 0,
                "loaned_amount": 0
            }
        ]
    }
}{
    "agendhoragoro6244": {
        "teams": []
    }
}{
    "triciadones": {
        "teams": [
            {
                "id": 8599,
                "shortname": "mchs",
                "name": "Moreau Catholic High School",
                "category": "Schools",
                "image": {
                    "id": 378615,
                    "template_id": 1
                },
                "whereabouts": "Hayward, CA",
                "loan_because": "Moreau Catholic High School is founded by the Congregation of Holy Cross. We are dedicated to transforming students into responsible citizens of our global community. ",
                "description": "High School students learning how their financial support can help to transform the lives of others. ",
                "website_url": "www.moreaucatholic.org",
                "team_since": "2009-08-27T19:20:11Z",
                "membership_type": "closed",
                "member_count": 955,
                "loan_count": 513,
                "loaned_amount": 14525
            }
        ]
    }
}{
    "kara2549": {
        "teams": [
            {
                "id": 394,
                "shortname": "nerdfighters",
                "name": "Nerdfighters",
                "category": "Common Interest",
                "image": {
                    "id": 1364412,
                    "template_id": 1
                },
                "whereabouts": "Nerdfighteria",
                "loan_because": "We aim to decrease world suck.\r\n\r\nAnd this is how:\r\nwww.eludehcs.no/kiva/nerdfighters/nerdfighters20120916.png by Nerdfighter Ole Bendik",
                "description": "We're Nerdfighters! We fight against suck; we fight for awesome! We fight using our brains, our hearts, our calculators, and our trombones.\r\n\r\nHappy lending!\r\n\r\nFollow us on twitter: https://twitter.com/KivaNerds",
                "website_url": "youtube.com/vlogbrothers",
                "team_since": "2008-09-02T16:26:24Z",
                "membership_type": "open",
                "member_count": 47565,
                "loan_count": 160855,
                "loaned_amount": 4745950
            }
        ]
    }
}{
    "leila8675": {
        "teams": []
    }
}{
    "william5414": {
        "teams": []
    }
}{
    "brandon5606": {
        "teams": [
            {
                "id": 2016,
                "shortname": "lawyers_and_law_students",
                "name": "Lawyers and Law Students Worldwide",
                "category": "Alumni Groups",
                "image": {
                    "id": 214588,
                    "template_id": 1
                },
                "whereabouts": "worldwide",
                "loan_because": "We believe everyone deserves an equal opportunity in life. \r\n\r\nFairness and justice are important to lawyers and law students. We hate to see things that are unfair. It is unfair that some people are born with lots of opportunities while others are born into extreme poverty. \r\n\r\nWe lend to try to correct this economic unfairness/injustice. We lend so that people in poverty can have the opportunity to build a good life for themselves and their families. ",
                "description": "Lawyers and Law Students from around  the World uniting to stop poverty and to give people a 'step up' so that they can help themselves. ",
                "website_url": "",
                "team_since": "2008-10-16T12:54:49Z",
                "membership_type": "open",
                "member_count": 53,
                "loan_count": 449,
                "loaned_amount": 12300
            },
            {
                "id": 4746,
                "shortname": "students_for_kiva",
                "name": "Students for Kiva",
                "category": "Common Interest",
                "image": {
                    "id": 265089,
                    "template_id": 1
                },
                "whereabouts": "Everywhere",
                "loan_because": "We care",
                "description": "Students across the world.",
                "website_url": "",
                "team_since": "2009-02-02T01:41:20Z",
                "membership_type": "open",
                "member_count": 15,
                "loan_count": 33,
                "loaned_amount": 825
            },
            {
                "id": 15331,
                "shortname": "st_marys_",
                "name": "St. Mary's Family ",
                "category": "Colleges/Universities",
                "image": {
                    "id": 609990,
                    "template_id": 1
                },
                "whereabouts": "San Antonio, TX",
                "loan_because": "",
                "description": "",
                "website_url": "",
                "team_since": "2010-09-29T16:20:10Z",
                "membership_type": "open",
                "member_count": 2,
                "loan_count": 0,
                "loaned_amount": 0
            }
        ]
    }
}{
    "carlo2381": {
        "teams": [
            {
                "id": 13441,
                "shortname": "team_itasa",
                "name": "Team Itasa",
                "category": "Common Interest",
                "image": {
                    "id": 561591,
                    "template_id": 1
                },
                "whereabouts": "Italy",
                "loan_because": "",
                "description": "we share love for tv series and helping people make a better living for themselves :)",
                "website_url": "",
                "team_since": "2010-05-07T11:22:30Z",
                "membership_type": "open",
                "member_count": 27,
                "loan_count": 371,
                "loaned_amount": 9550
            }
        ]
    }
}{
    "zapprocc8276": {
        "teams": []
    }
}{
    "bridget6305": {
        "teams": []
    }
}{
    "believe3586": {
        "teams": []
    }
}{
    "ixwarez7963": {
        "teams": []
    }
}{
    "steven6403": {
        "teams": []
    }
}{
    "ruth22298288": {
        "teams": []
    }
}{
    "jestiaddeme3306": {
        "teams": []
    }
}{
    "tai7092": {
        "teams": [
            {
                "id": 191,
                "shortname": "fsm",
                "name": "Church of the Flying Spaghetti Monster",
                "category": "Religious Congregations",
                "image": {
                    "id": 196261,
                    "template_id": 1
                },
                "whereabouts": "Earth",
                "loan_because": "\"Thou shalt share, that none may seek without funding.\"   A nod to VII.  of “RANDOM NUMBER OF NOT COMMANDMENTS, SUGGESTIONS\"  in the LOOSE CANON:\r\nhttp://www.loose-canon.info/page17.htm",
                "description": "Members of the Church of the Flying Spaghetti Monster  \r\n\r\nSecular vs religious Field Partners, see links at http://atheist-monkey.blogspot.de/2009/08/kiva-mfi-checker.html\r\n\r\nFor Kiva tips and who knows what the FSM will move us to add for mutual benefit & merriment:  \r\nhttp://flyingspaghettikivans.blogspot.it/    \r\n\r\nand\r\n  https://www.facebook.com/pages/FlyingSpaghettiKivans\r\n",
                "website_url": "http://www.venganza.org",
                "team_since": "2008-08-30T09:37:51Z",
                "membership_type": "open",
                "member_count": 4224,
                "loan_count": 80780,
                "loaned_amount": 2308475
            },
            {
                "id": 94,
                "shortname": "atheists",
                "name": "Atheists, Agnostics, Skeptics, Freethinkers, Secular Humanists and the Non-Religious",
                "category": "Common Interest",
                "image": {
                    "id": 1401504,
                    "template_id": 1
                },
                "whereabouts": "Earth",
                "loan_because": "We care about human beings and understand that it takes people to help people.",
                "description": "We are one human family, and we know that people can do good without believing in a god.\r\n\r\nThe Plus sign in the A+ Team logo reflects the fact that the team comprises Atheists, PLUS Agnostics, Skeptics, Freethinkers, Secular Humanists, and Non-Religious members.  A+ is also a symbol of excellence.\r\n\r\n***TEAM WEBSITE***\r\nhttp://apluskiva.wordpress.com/\r\n\r\n***TEAM RESOURCES***\r\nSecular Loans\r\nhttp://goo.gl/wtDkJ\r\n\r\nField Partners - Social and Secular Ratings:\r\nwww.tinyurl.com/AASFSHNR-MFIs\r\n\r\n***OTHER RESOURCES:***\r\nStarfish List:\r\nhttp://starfish.dynalias.org/\r\n\r\nKivaLens:\r\nhttp://www.kivalens.org/\r\n\r\nToolkit for analyzing Kiva data:\r\nhttp://build.kiva.org/",
                "website_url": "http://apluskiva.wordpress.com/",
                "team_since": "2008-08-29T03:40:31Z",
                "membership_type": "open",
                "member_count": 30456,
                "loan_count": 611640,
                "loaned_amount": 17850225
            },
            {
                "id": 116,
                "shortname": "australia",
                "name": "Australia",
                "category": "Local Area",
                "image": {
                    "id": 195915,
                    "template_id": 1
                },
                "whereabouts": "Australia",
                "loan_because": "Australians all let us rejoice\r\nfor we are young and free,    -   \r\nWe've heard the call of nations wide,\r\nHow can we let this be?    -   \r\nWe'll share our wealth,\r\nWe'll make the change,\r\nWe'll help to set them free   -   \r\nFrom us to them\r\nand back again, \r\nAs one we all shall be      - \r\n\r\n(Thanks to member Jean for this one)\r\n\r\nFind us on Facebook at http://www.facebook.com/group.php?gid=97953452142",
                "description": "Kiva Loaners in Australia",
                "website_url": "",
                "team_since": "2008-08-29T14:32:01Z",
                "membership_type": "open",
                "member_count": 5906,
                "loan_count": 172377,
                "loaned_amount": 4706375
            },
            {
                "id": 15349,
                "shortname": "allsafe",
                "name": "AllSafe",
                "category": "Businesses",
                "image": {
                    "id": 610891,
                    "template_id": 1
                },
                "whereabouts": "Bundaberg Australia",
                "loan_because": "Our philosophy is both straight forward and simple, yet incredibly powerful. It drives everything we do – from selecting the products and services we offer, to deciding which charities to support.\r\n\r\nCommunity Awareness – AllSafe has the ultimate goal of giving back to the community wherever possible.   AllSafe supports Kiva because it is a community based project, offering assistance, support and shelter, mentoring, counselling and advice to the most underprivileged, needy and vulnerable in our global community.\r\n\r\n   \r\n  \r\nMake an enquiry\r\n* Required information.\r\n\r\nFirst Name * \r\nSurname * \r\nPhone * \r\nEmail * \r\nAddress \r\nSuburb \r\nPost Code * \r\nState \r\n\r\nCountry * \r\nComments\r\n\r\nHow did you find out about us? *\r\n\r\n \r\n",
                "description": "AllSafe Energy Efficient Products aims to deliver solutions and savings to you and the environment through ‘minimizing your carbon footprint.' \r\n\r\nWe specialise in a wide variety of energy saving products like insulation, syklights and solar hot-water systems, as well as a range of  solar and wind power generator solutions.\r\n\r\nAllSafe Energy Efficient Products is recognized as one of the leading and fastest growing energy efficient product providers in Australia. Whilst many companies offer energy efficient products and services they only offer a small or restricted range – perhaps just insulation, or only solar hot water services. In AllSafe’s view, these are not the “solutions” that consumers demand today and will increasingly demand tomorrow.\r\n\r\nAllSafe Energy Efficient Products has a broad range of products and services so it can truly offer energy efficient solutions across the whole of the customer’s home, factory or office.\r\n",
                "website_url": "all-safe.com.au",
                "team_since": "2010-10-01T03:48:51Z",
                "membership_type": "open",
                "member_count": 2,
                "loan_count": 106,
                "loaned_amount": 2650
            },
            {
                "id": 17605,
                "shortname": "sciencewins",
                "name": "Science Wins Every Time",
                "category": "Common Interest",
                "image": {
                    "id": 696466,
                    "template_id": 1
                },
                "whereabouts": "The Human Mind",
                "loan_because": "Accident of birthplace should no longer be an impediment to prosperity.",
                "description": "We believe that science is our best tool for learning about the world around us.\r\n\r\nWe feel that scientific literacy is essential for problem solving in the modern world.\r\n\r\nWe are thankful for the insights and technologies that the scientific method has produced, and hope that its role in the future of our species will continue to grow.",
                "website_url": "http://www.youtube.com/user/ScienceWinsEveryTime",
                "team_since": "2011-01-19T22:25:22Z",
                "membership_type": "open",
                "member_count": 16,
                "loan_count": 44,
                "loaned_amount": 1100
            }
        ]
    }
}{
    "johnvone8705": {
        "teams": []
    }
}{
    "impulsesport3529": {
        "teams": []
    }
}{
    "opsdigfu9637": {
        "teams": []
    }
}{
    "rebekah9195": {
        "teams": []
    }
}{
    "mfjason7518": {
        "teams": []
    }
}{
    "rebecka1358": {
        "teams": [
            {
                "id": 15136,
                "shortname": "sverok",
                "name": "Sverok",
                "category": "Common Interest",
                "image": {
                    "id": 1436407,
                    "template_id": 1
                },
                "whereabouts": "Sverige",
                "loan_because": "Många i Sverok känner ett engagemang för sin omvärld och för sina medmänniskor!",
                "description": "Vi är medlemmar i Sverok, Sveriges största ungdomsförbund.",
                "website_url": "www.sverok.se",
                "team_since": "2010-09-17T07:34:28Z",
                "membership_type": "open",
                "member_count": 19,
                "loan_count": 569,
                "loaned_amount": 14425
            }
        ]
    }
}{
    "zmynd1185": {
        "teams": [
            {
                "id": 15147,
                "shortname": "we_are_here_for_you",
                "name": "We are here for You",
                "category": "Friends",
                "image": {
                    "id": 602494,
                    "template_id": 1
                },
                "whereabouts": "China",
                "loan_because": "We want to help people who want to help themsleves to have a better life.",
                "description": "We are  friends sharing the same opinion: we can do more to commit ourselves into the world",
                "website_url": "",
                "team_since": "2010-09-18T08:03:37Z",
                "membership_type": "open",
                "member_count": 20,
                "loan_count": 0,
                "loaned_amount": 0
            }
        ]
    }
}{
    "gede8763": {
        "teams": [
            {
                "id": 11617,
                "shortname": "windstar_cruises",
                "name": "Windstar Cruises",
                "category": "Alumni Groups",
                "image": {
                    "id": 469751,
                    "template_id": 1
                },
                "whereabouts": "Seattle, WA",
                "loan_because": "Windstar Cruises supports KIVA's work in alleviating poverty through  small business micro-lending. We invite past and future Windstar  guests to connect through our team and join us in supporting this worthwhile cause to help end poverty in developing countries.  ",
                "description": "Windstar Cruises operates three sailing yachts (Wind Spirit, Wind Star, Wind Surf) known for their pampering without pretense and their ability to visit the hidden harbors and secluded coves of the world’s most treasured destinations.  Carrying just 148 to 312 guests, the luxurious ships of Windstar cruise to nearly 50 nations, calling at 100 ports throughout Europe, the Caribbean and the Americas. For more information including brochures, rates and itineraries contact a professional travel agent or call Windstar at 1-800-258-7245. Visit Windstar Cruises online at www.windstarcruises.com. \r\n\r\n",
                "website_url": "www.windstarcruises.com",
                "team_since": "2010-01-14T19:51:15Z",
                "membership_type": "open",
                "member_count": 31,
                "loan_count": 145,
                "loaned_amount": 3650
            }
        ]
    }
}{
    "nancyduan": {
        "teams": [
            {
                "id": 97,
                "shortname": "berkeley",
                "name": "UC Berkeley Campus Kiva",
                "category": "Colleges/Universities",
                "image": {
                    "id": 195778,
                    "template_id": 1
                },
                "whereabouts": "Berkeley, CA",
                "loan_because": "",
                "description": "",
                "website_url": "",
                "team_since": "2008-08-29T05:13:03Z",
                "membership_type": "open",
                "member_count": 271,
                "loan_count": 4246,
                "loaned_amount": 111850
            }
        ]
    }
}{
    "dtynan": {
        "teams": [
            {
                "id": 94,
                "shortname": "atheists",
                "name": "Atheists, Agnostics, Skeptics, Freethinkers, Secular Humanists and the Non-Religious",
                "category": "Common Interest",
                "image": {
                    "id": 1401504,
                    "template_id": 1
                },
                "whereabouts": "Earth",
                "loan_because": "We care about human beings and understand that it takes people to help people.",
                "description": "We are one human family, and we know that people can do good without believing in a god.\r\n\r\nThe Plus sign in the A+ Team logo reflects the fact that the team comprises Atheists, PLUS Agnostics, Skeptics, Freethinkers, Secular Humanists, and Non-Religious members.  A+ is also a symbol of excellence.\r\n\r\n***TEAM WEBSITE***\r\nhttp://apluskiva.wordpress.com/\r\n\r\n***TEAM RESOURCES***\r\nSecular Loans\r\nhttp://goo.gl/wtDkJ\r\n\r\nField Partners - Social and Secular Ratings:\r\nwww.tinyurl.com/AASFSHNR-MFIs\r\n\r\n***OTHER RESOURCES:***\r\nStarfish List:\r\nhttp://starfish.dynalias.org/\r\n\r\nKivaLens:\r\nhttp://www.kivalens.org/\r\n\r\nToolkit for analyzing Kiva data:\r\nhttp://build.kiva.org/",
                "website_url": "http://apluskiva.wordpress.com/",
                "team_since": "2008-08-29T03:40:31Z",
                "membership_type": "open",
                "member_count": 30456,
                "loan_count": 611640,
                "loaned_amount": 17850225
            },
            {
                "id": 117,
                "shortname": "team_europe",
                "name": "Team Europe",
                "category": "Local Area",
                "image": {
                    "id": 195919,
                    "template_id": 1
                },
                "whereabouts": "Europe",
                "loan_because": "We think Kiva is a unique opportunity for people all over the world to assist entrepreneurs in improving their businesses and communities.",
                "description": "We are European lenders (EU, EFTA, and all those who feel they belong) who share the belief in Kiva's vision.",
                "website_url": "",
                "team_since": "2008-08-29T14:45:05Z",
                "membership_type": "open",
                "member_count": 4924,
                "loan_count": 123408,
                "loaned_amount": 3718750
            },
            {
                "id": 108,
                "shortname": "ireland",
                "name": "Ireland",
                "category": "Local Area",
                "image": {
                    "id": 195850,
                    "template_id": 1
                },
                "whereabouts": "Ireland",
                "loan_because": "Small streams become mighty rivers.",
                "description": "A group of Kiva Lenders from Ireland, or with links to Ireland. Feel free to join our community :)",
                "website_url": "",
                "team_since": "2008-08-29T11:49:19Z",
                "membership_type": "open",
                "member_count": 425,
                "loan_count": 7663,
                "loaned_amount": 228325
            },
            {
                "id": 22527,
                "shortname": "beoga",
                "name": "Beoga",
                "category": "Friends",
                "whereabouts": "Galway",
                "loan_because": "We can",
                "description": "",
                "website_url": "",
                "team_since": "2011-12-26T15:45:28Z",
                "membership_type": "open",
                "member_count": 9,
                "loan_count": 69,
                "loaned_amount": 1875
            },
            {
                "id": 28899,
                "shortname": "hp",
                "name": "HP",
                "category": "Businesses - Internal Groups",
                "image": {
                    "id": 1496655,
                    "template_id": 1
                },
                "whereabouts": "",
                "loan_because": "This is a unique opportunity for HP employees globally to actively participate in driving HP Living Progress by supporting thousands of entrepreneurs around the world who need access to capital to start or grow their business. HP Living Progress is the framework for how we do business. It’s how we use our people and technologies to create a world where everyone has the opportunity to progress. \r\n\r\nThrough this innovative collaboration with Kiva and the HP Company Foundation we can help ensure that entrepreneurs around the world achieve their dreams.",
                "description": "Our team is committed to changing a million lives, and helping to end extreme poverty, one loan at a time.",
                "website_url": "www.hp.com",
                "team_since": "2013-12-19T20:06:51Z",
                "membership_type": "open",
                "member_count": 121648,
                "loan_count": 191252,
                "loaned_amount": 5943200
            }
        ]
    }
}{
    "andreas9605": {
        "teams": []
    }
}{
    "clancy2501": {
        "teams": []
    }
}{
    "hoadyhano4025": {
        "teams": []
    }
}{
    "ukraudio8751": {
        "teams": []
    }
}{
    "magnus5591": {
        "teams": [
            {
                "id": 84,
                "shortname": "sweden",
                "name": "Sweden",
                "category": "Local Area",
                "image": {
                    "id": 195707,
                    "template_id": 1
                },
                "whereabouts": "Sweden",
                "loan_because": "",
                "description": "Sometimes it's easier to see that what a difference we each make by looking at what we do together -- And having more people together might even convince others to join and lend as well. Feel free to join up if you're a Kiva member in Sweden!",
                "website_url": "",
                "team_since": "2008-08-28T21:54:53Z",
                "membership_type": "open",
                "member_count": 1386,
                "loan_count": 45678,
                "loaned_amount": 1336300
            }
        ]
    }
}{
    "repekeerorp1735": {
        "teams": []
    }
}{
    "asprlingam4004": {
        "teams": []
    }
}{
    "your6873": {
        "teams": []
    }
}{
    "thomas8993": {
        "teams": []
    }
}{
    "ellenbeth2495": {
        "teams": [
            {
                "id": 94,
                "shortname": "atheists",
                "name": "Atheists, Agnostics, Skeptics, Freethinkers, Secular Humanists and the Non-Religious",
                "category": "Common Interest",
                "image": {
                    "id": 1401504,
                    "template_id": 1
                },
                "whereabouts": "Earth",
                "loan_because": "We care about human beings and understand that it takes people to help people.",
                "description": "We are one human family, and we know that people can do good without believing in a god.\r\n\r\nThe Plus sign in the A+ Team logo reflects the fact that the team comprises Atheists, PLUS Agnostics, Skeptics, Freethinkers, Secular Humanists, and Non-Religious members.  A+ is also a symbol of excellence.\r\n\r\n***TEAM WEBSITE***\r\nhttp://apluskiva.wordpress.com/\r\n\r\n***TEAM RESOURCES***\r\nSecular Loans\r\nhttp://goo.gl/wtDkJ\r\n\r\nField Partners - Social and Secular Ratings:\r\nwww.tinyurl.com/AASFSHNR-MFIs\r\n\r\n***OTHER RESOURCES:***\r\nStarfish List:\r\nhttp://starfish.dynalias.org/\r\n\r\nKivaLens:\r\nhttp://www.kivalens.org/\r\n\r\nToolkit for analyzing Kiva data:\r\nhttp://build.kiva.org/",
                "website_url": "http://apluskiva.wordpress.com/",
                "team_since": "2008-08-29T03:40:31Z",
                "membership_type": "open",
                "member_count": 30456,
                "loan_count": 611640,
                "loaned_amount": 17850225
            }
        ]
    }
}{
    "syedasif1076": {
        "teams": []
    }
}{
    "nagaraj1864": {
        "teams": []
    }
}{
    "joseluis9182": {
        "teams": [
            {
                "id": 15278,
                "shortname": "cantabria_20",
                "name": "Cantabria 2.0",
                "category": "Common Interest",
                "image": {
                    "id": 607424,
                    "template_id": 1
                },
                "whereabouts": "Cantabria",
                "loan_because": "",
                "description": "Internautas cántabros con ganas de ayudar a gente que tiene ganas de ayudarse",
                "website_url": "http://twitter.com/twiterruca",
                "team_since": "2010-09-25T23:04:49Z",
                "membership_type": "open",
                "member_count": 34,
                "loan_count": 544,
                "loaned_amount": 13750
            },
            {
                "id": 312,
                "shortname": "spain_team",
                "name": "España - Spain",
                "category": "Local Area",
                "image": {
                    "id": 196940,
                    "template_id": 1
                },
                "whereabouts": "España (Spain)",
                "loan_because": "Kiva ofrece un medio ideal para participar activamente en el apoyo a emprendedores sin recursos que no pueden acceder a los canales normales de financiación y que, gracias a los micro-créditos, pueden  desarrollar una actividad empresarial que les permita, a ellos y su entorno, alcanzar una mejor calidad de vida. ",
                "description": "Este club se creó con la intención inicial de fomentar la participación de españolas y españoles en Kiva, no obstante,  está abierto a todas las personas que deseen unirse a él, sin importar su nacionalidad ni ninguna otra condición.\r\n \r\nEl único referente identitario de este grupo es la solidaridad y la convicción de que, a través de Kiva, es posible el apoyo a personas o grupos emprendedores que buscan y merecen una oportunidad por su esfuerzo.\r\n",
                "website_url": "",
                "team_since": "2008-08-31T23:59:17Z",
                "membership_type": "open",
                "member_count": 649,
                "loan_count": 23229,
                "loaned_amount": 651250
            }
        ]
    }
}{
    "larry51038127": {
        "teams": []
    }
}{
    "elisabeth3128": {
        "teams": []
    }
}{
    "alfred6767": {
        "teams": [
            {
                "id": 15283,
                "shortname": "team_tali",
                "name": "team tali",
                "category": "Friends",
                "whereabouts": "marblehead massachusetts",
                "loan_because": "we want to give people a chance to succeed.",
                "description": "a group of kids and parents that feel we can make the world a better place.",
                "website_url": "",
                "team_since": "2010-09-26T15:45:00Z",
                "membership_type": "open",
                "member_count": 21,
                "loan_count": 31,
                "loaned_amount": 800
            }
        ]
    }
}{
    "michael2352": {
        "teams": []
    }
}{
    "nora6287": {
        "teams": []
    }
}{
    "tisenaida5967": {
        "teams": []
    }
}{
    "andrewbalak7056": {
        "teams": []
    }
}{
    "alison87692918": {
        "teams": []
    }
}{
    "benson2516": {
        "teams": [
            {
                "id": 283,
                "shortname": "christians",
                "name": "Kiva Christians",
                "category": "Friends",
                "image": {
                    "id": 471653,
                    "template_id": 1
                },
                "whereabouts": "Worldwide",
                "loan_because": "Pure and undefiled religion before God the Father is this: to care for orphans and widows in their misfortune and to keep oneself unstained by the world. (Jam. 1:27) http://whoisjesus-really.com/\r\n\r\nLink to information regarding Christian partners       \r\nhttp://goo.gl/LU3hzz",
                "description": "A group of believers in Jesus Christ, brought together through a common purpose: to help those in need around the world.    \r\n",
                "website_url": "http://whoisjesus-really.com/",
                "team_since": "2008-08-31T15:33:31Z",
                "membership_type": "open",
                "member_count": 14398,
                "loan_count": 360702,
                "loaned_amount": 14006650
            }
        ]
    }
}{
    "melissa5629": {
        "teams": []
    }
}{
    "naotoshi6590": {
        "teams": [
            {
                "id": 15310,
                "shortname": "pororocca",
                "name": "POROROCCA",
                "category": "Other",
                "image": {
                    "id": 608897,
                    "template_id": 1
                },
                "whereabouts": "JAPAN",
                "loan_because": "",
                "description": "",
                "website_url": "",
                "team_since": "2010-09-28T11:39:23Z",
                "membership_type": "open",
                "member_count": 3,
                "loan_count": 0,
                "loaned_amount": 0
            }
        ]
    }
}{
    "kapil3202": {
        "teams": []
    }
}{
    "greenbay2721": {
        "teams": [
            {
                "id": 18810,
                "shortname": "greenbay_by_olympia",
                "name": "GREENbay by Olympia",
                "category": "Businesses",
                "image": {
                    "id": 734103,
                    "template_id": 1
                },
                "whereabouts": "Bayreuth Germany",
                "loan_because": "GREENbay is our token to affection for the planet we share. Because it´s better to live than to be lived. Because it´s better to have fun than to be annoyed. Because it´s better to get on with each other than to fight over nothing",
                "description": "We´re a young brand and  we love good ideas all over the world, quite the same wether they´re big or small.",
                "website_url": "www.eco-bikini.de",
                "team_since": "2011-03-18T12:12:18Z",
                "membership_type": "open",
                "member_count": 1,
                "loan_count": 23,
                "loaned_amount": 575
            }
        ]
    }
}{
    "jabydonodob4545": {
        "teams": []
    }
}{
    "rva": {
        "teams": []
    }
}